databyte/__init__.py
databyte/admin.py
databyte/apps.py
databyte/fields.py
databyte/models.py
databyte/signals.py
databyte/tests.py
databyte/utils.py
databyte/views.py
databyte/migrations/__init__.py
databyte-1.3.dist-info/LICENSE
databyte-1.3.dist-info/METADATA
databyte-1.3.dist-info/WHEEL
databyte-1.3.dist-info/top_level.txt
databyte-1.3.dist-info/RECORD
