Metadata-Version: 2.1
Name: databyte
Version: 1.3
Summary: A Django app to help keep track of storage usage by records.
Home-page: https://github.com/YidiSprei/DjangoDatabyte.git
Author: Yidi Sprei
Author-email: yidi.sprei@infuzu.com
License: MIT License
Classifier: Environment :: Web Environment
Classifier: Framework :: Django
Classifier: Intended Audience :: Developers
Classifier: License :: OSI Approved :: MIT License
Classifier: Operating System :: OS Independent
Classifier: Programming Language :: Python
Classifier: Programming Language :: Python :: 3
Classifier: Topic :: Internet :: WWW/HTTP
Classifier: Topic :: Internet :: WWW/HTTP :: Dynamic Content
License-File: LICENSE
